pycoff/__init__.py
pycoff/ar.py
pycoff/coff.py
pycoff/defs.py
pycoff/elf.py
pycoff/node.py
pycoff/obj.py
pycoff/pe.py
pycoff/utils.py
pycoff/template/ar.json
pycoff/template/ar.py
pycoff/template/obj.json
pycoff/template/obj.py
pycoff/template/pe.json
pycoff/template/pe.py
pycoff/template/header/archive_member.json
pycoff/template/header/directories.json
pycoff/template/header/file.json
pycoff/template/header/import.json
pycoff/template/header/obj.json
pycoff/template/header/option.json
pycoff/template/header/option.py
pycoff/template/header/relocation.json
pycoff/template/header/section.json
pycoff-1.0.1.dist-info/LICENSE
pycoff-1.0.1.dist-info/METADATA
pycoff-1.0.1.dist-info/WHEEL
pycoff-1.0.1.dist-info/top_level.txt
pycoff-1.0.1.dist-info/RECORD
